pytyper_weather_forecast/__init__.py
pytyper_weather_forecast/main.py
pytyper_weather_forecast-0.2.0.dist-info/entry_points.txt
pytyper_weather_forecast-0.2.0.dist-info/METADATA
pytyper_weather_forecast-0.2.0.dist-info/WHEEL
pytyper_weather_forecast-0.2.0.dist-info/RECORD
